[
  {
    "barcode": "PEMENANG UNDIAN BAYAN RUN 2025\n\nNama: George Miracle\nBIB: 4231\nHadiah: Kaos Bayan Run 2025\nTelepon: 085377640809\nEmail: george.miracle@email.com\n\nSelamat anda memenangkan undian ini!\nSilakan tunjukkan QR code ini saat pengambilan hadiah.\n\nGenerated: 2025-09-29 17:59:45\nStatus: VALID",
    "meja": "meja1",
    "name": "George Miracle",
    "email": "Unknown",
    "timestamp": "2025-09-30T05:44:53.665Z"
  },
  {
    "barcode": "PEMENANG UNDIAN BAYAN RUN 2025\n\nNama: George Miracle\nBIB: 4231\nHadiah: Kaos Bayan Run 2025\nTelepon: 085377640809\nEmail: george.miracle@email.com\n\nSelamat anda memenangkan undian ini!\nSilakan tunjukkan QR code ini saat pengambilan hadiah.\n\nGenerated: 2025-09-29 18:03:55\nStatus: VALID",
    "meja": "meja1",
    "name": "George Miracle",
    "email": "Unknown",
    "timestamp": "2025-10-02T05:35:56.831Z"
  },
  {
    "barcode": "PEMENANG UNDIAN BAYAN RUN 2025\n\nNama: George Miracle\nBIB: 4231\nHadiah: Kaos Bayan Run 2025\nTelepon: 085377640809\nEmail: george.miracle@email.com\n\nSelamat anda memenangkan undian ini!\nSilakan tunjukkan QR code ini saat pengambilan hadiah.\n\nGenerated: 2025-09-29 17:58:09\nStatus: VALID",
    "meja": "meja1",
    "name": "George Miracle",
    "email": "Unknown",
    "timestamp": "2025-10-02T05:38:16.661Z"
  }
]